test/__init__.py
test/test_client.py
test/test_database.py
test/test_post.py
test/test_storage.py
wwricu/__init__.py
wwricu/config.py
wwricu/main.py
wwricu/middleware.py
wwricu/api/__init__.py
wwricu/api/common.py
wwricu/api/open.py
wwricu/api/post.py
wwricu/api/tag.py
wwricu/domain/__init__.py
wwricu/domain/common.py
wwricu/domain/entity.py
wwricu/domain/enum.py
wwricu/domain/input.py
wwricu/domain/output.py
wwricu/service/__init__.py
wwricu/service/cache.py
wwricu/service/common.py
wwricu/service/database.py
wwricu/service/post.py
wwricu/service/storage.py
wwricu/service/tag.py
wwricu-0.0.4.dist-info/METADATA
wwricu-0.0.4.dist-info/WHEEL
wwricu-0.0.4.dist-info/entry_points.txt
wwricu-0.0.4.dist-info/top_level.txt
wwricu-0.0.4.dist-info/RECORD
