Metadata-Version: 2.2
Name: wwricu
Version: 0.0.4
Summary: wwr.icu api service
Requires-Python: >=3.12
Requires-Dist: aiosqlite==0.20.0
Requires-Dist: bcrypt==4.2.1
Requires-Dist: boto3==1.35.90
Requires-Dist: fastapi==0.115.6
Requires-Dist: python-multipart==0.0.19
Requires-Dist: SQLAlchemy==2.0.36
Requires-Dist: uvicorn==0.32.1
